rpcore/__init__.py
rpcore/common_resources.py
rpcore/effect.py
rpcore/globals.py
rpcore/gpu_command_queue.py
rpcore/image.py
rpcore/light_manager.py
rpcore/loader.py
rpcore/mount_manager.py
rpcore/render_pipeline.py
rpcore/render_stage.py
rpcore/render_target.py
rpcore/rpobject.py
rpcore/stage_manager.py
rpcore/gui/__init__.py
rpcore/gui/buffer_viewer.py
rpcore/gui/checkbox.py
rpcore/gui/checkbox_collection.py
rpcore/gui/debugger.py
rpcore/gui/draggable_window.py
rpcore/gui/error_message_display.py
rpcore/gui/exposure_widget.py
rpcore/gui/fps_chart.py
rpcore/gui/labeled_checkbox.py
rpcore/gui/loading_screen.py
rpcore/gui/pipe_viewer.py
rpcore/gui/pixel_inspector.py
rpcore/gui/render_mode_selector.py
rpcore/gui/slider.py
rpcore/gui/sprite.py
rpcore/gui/text.py
rpcore/gui/text_node.py
rpcore/gui/texture_preview.py
rpcore/native/__init__.py
rpcore/native/update_module_builder.py
rpcore/pluginbase/__init__.py
rpcore/pluginbase/base_plugin.py
rpcore/pluginbase/day_manager.py
rpcore/pluginbase/day_setting_types.py
rpcore/pluginbase/manager.py
rpcore/pluginbase/setting_types.py
rpcore/pynative/__init__.py
rpcore/pynative/gpu_command.py
rpcore/pynative/gpu_command_list.py
rpcore/pynative/ies_dataset.py
rpcore/pynative/internal_light_manager.py
rpcore/pynative/pointer_slot_storage.py
rpcore/pynative/pssm_camera_rig.py
rpcore/pynative/rp_light.py
rpcore/pynative/rp_point_light.py
rpcore/pynative/rp_spot_light.py
rpcore/pynative/shadow_atlas.py
rpcore/pynative/shadow_manager.py
rpcore/pynative/shadow_source.py
rpcore/pynative/tag_state_manager.py
rpcore/stages/__init__.py
rpcore/stages/ambient_stage.py
rpcore/stages/apply_lights_stage.py
rpcore/stages/collect_used_cells_stage.py
rpcore/stages/combine_velocity_stage.py
rpcore/stages/cull_lights_stage.py
rpcore/stages/downscale_z_stage.py
rpcore/stages/final_stage.py
rpcore/stages/flag_used_cells_stage.py
rpcore/stages/gbuffer_stage.py
rpcore/stages/shadow_stage.py
rpcore/stages/update_previous_pipes_stage.py
panda3d_Pipeline-0.0.2.dist-info/METADATA
panda3d_Pipeline-0.0.2.dist-info/WHEEL
panda3d_Pipeline-0.0.2.dist-info/top_level.txt
panda3d_Pipeline-0.0.2.dist-info/RECORD
